[
 {
  "table":"DDDDLSRC",
  "data":
  [
   {
    "DDLNAME":"ZYCDS_DUE_MAT_LIST2",
    "AS4LOCAL":"N",
    "AS4USER":"SAP_CUSTOMER",
    "AS4DATE":"0000-00-00",
    "AS4TIME":"00:00:00",
    "SOURCE":"@AbapCatalog.viewEnhancementCategory: [#NONE]\r\n@AccessControl.authorizationCheck: #NOT_REQUIRED\r\n@EndUserText.label: 'Material Due Date List'\r\n@Metadata.ignorePropagatedAnnotations: true\r\n@ObjectModel.usageType:{\r\n    serviceQuality: #X, \r\n    sizeCategory: #S,\r\n    dataClass: #MIXED\r\n}\r\n@Metadata.allowExtensions: true\r\ndefine root view entity ZYCDS_DUE_MAT_LIST2 as select from ZYCDS_DUE_MAT_LIST\r\nassociation [1..1] to I_StorageLocation on I_StorageLocation.StorageLocation = ZYCDS_DUE_MAT_LIST.StorageLocation\r\n                                       and I_StorageLocation.Plant           = ZYCDS_DUE_MAT_LIST.Plant\r\n association [0..1] to zydc_config_cds_poc as _Config on ZYCDS_DUE_MAT_LIST.Remaining_days >= _Config.daysfrom  \r\n                               and ZYCDS_DUE_MAT_LIST.Remaining_days <= _Config.daysto                            \r\n{\r\n  key ZYCDS_DUE_MAT_LIST.Material,\r\n  key ZYCDS_DUE_MAT_LIST.Plant,\r\n  key ZYCDS_DUE_MAT_LIST.StorageLocation,\r\n  key ZYCDS_DUE_MAT_LIST.Batch,\r\n  key ZYCDS_DUE_MAT_LIST.Supplier,\r\n//  key YCDS_DUE_MAT_LIST.InventoryStockType,\r\n//  key YCDS_DUE_MAT_LIST.MatlDocLatestPostgDate,\r\n  ZYCDS_DUE_MAT_LIST.ProductDescription,\r\n  ZYCDS_DUE_MAT_LIST.PlantName,\r\n  I_StorageLocation.StorageLocationName,\r\n  ZYCDS_DUE_MAT_LIST.BatchBySupplier,\r\n  ZYCDS_DUE_MAT_LIST.SupplierName,\r\n//  MatlWrhsStkQtyInMatlBaseUnit,\r\n  ZYCDS_DUE_MAT_LIST.BaseUnit, \r\n  @Semantics.quantity.unitOfMeasure: 'BaseUnit'\r\n  MatlWrhsStkQtyInMatlBaseUnit,\r\n  MatlBatchIsInRstrcdUseStock,\r\n  ZYCDS_DUE_MAT_LIST.ShelfLifeExpirationDate,\r\n  ZYCDS_DUE_MAT_LIST.ManufactureDate,\r\n  ZYCDS_DUE_MAT_LIST.BatchStatus,\r\n  Remaining_days, \r\n     _Config.criticality as Criticality,\r\n  _Config.remarks as Due_range\r\n    \r\n    \r\n//     cast( '0' as abap.int1 ) as Criticality\r\n}  where _Config.remarks != '0'\r\n/*+[internal] {\n\"BASEINFO\":\n{\n\"FROM\":\n[\n\"I_STORAGELOCATION\",\n\"ZYCDS_DUE_MAT_LIST\",\n\"ZYDC_CONFIG_CDS_POC\"\n],\n\"ASSOCIATED\":\n[],\n\"BASE\":\n[],\n\"ANNO_REF\":\n[],\n\"SCALAR_FUNCTION\":\n[],\n\"VERSION\":0,\n\"ANNOREF_EVALUATION_ERROR\":\"\"\n}\n}*/",
    "PARENTNAME":"",
    "ACTFLAG":"",
    "CHGFLAG":"",
    "SOURCE_TYPE":"W",
    "SOURCE_ORIGIN":"0",
    "ABAP_LANGUAGE_VERSION":"5"
   }
  ]
 },
 {
  "table":"DDDDLSRC02BT",
  "data":
  [
   {
    "DDLNAME":"ZYCDS_DUE_MAT_LIST2",
    "STRUCOBJN":"ZYCDS_DUE_MAT_LIST2",
    "DDLANGUAGE":"E",
    "AS4LOCAL":"N",
    "DDTEXT":"Material Due Date List"
   }
  ]
 },
 {
  "table":"DDDDLSRCT",
  "data":
  [
   {
    "DDLNAME":"ZYCDS_DUE_MAT_LIST2",
    "DDLANGUAGE":"E",
    "AS4LOCAL":"N",
    "DDTEXT":"Material Due Date List"
   }
  ]
 },
 {
  "table":"DDFIELDANNO",
  "data":
  [
   {
    "STRUCOBJN":"ZYCDS_DUE_MAT_LIST2",
    "LFIELDNAME":"MANDT",
    "NAME":"ABAPCATALOG",
    "POSITION":1,
    "VALUE":""
   },
   {
    "STRUCOBJN":"ZYCDS_DUE_MAT_LIST2",
    "LFIELDNAME":"MANDT",
    "NAME":"ABAPCATALOG.INTERNAL.ISMANDT",
    "POSITION":2,
    "VALUE":""
   },
   {
    "STRUCOBJN":"ZYCDS_DUE_MAT_LIST2",
    "LFIELDNAME":"MATLWRHSSTKQTYINMATLBASEUNIT",
    "NAME":"SEMANTICS",
    "POSITION":3,
    "VALUE":""
   },
   {
    "STRUCOBJN":"ZYCDS_DUE_MAT_LIST2",
    "LFIELDNAME":"MATLWRHSSTKQTYINMATLBASEUNIT",
    "NAME":"SEMANTICS.QUANTITY.UNITOFMEASURE",
    "POSITION":4,
    "VALUE":"'BaseUnit'"
   }
  ]
 },
 {
  "table":"DDHEADANNO",
  "data":
  [
   {
    "STRUCOBJN":"ZYCDS_DUE_MAT_LIST2",
    "NAME":"ABAPCATALOG",
    "POSITION":1,
    "VALUE":""
   },
   {
    "STRUCOBJN":"ZYCDS_DUE_MAT_LIST2",
    "NAME":"ABAPCATALOG.VIEWENHANCEMENTCATEGORY$1$",
    "POSITION":2,
    "VALUE":"#NONE"
   },
   {
    "STRUCOBJN":"ZYCDS_DUE_MAT_LIST2",
    "NAME":"ACCESSCONTROL",
    "POSITION":3,
    "VALUE":""
   },
   {
    "STRUCOBJN":"ZYCDS_DUE_MAT_LIST2",
    "NAME":"ACCESSCONTROL.AUTHORIZATIONCHECK",
    "POSITION":4,
    "VALUE":"#NOT_REQUIRED"
   },
   {
    "STRUCOBJN":"ZYCDS_DUE_MAT_LIST2",
    "NAME":"ENDUSERTEXT",
    "POSITION":5,
    "VALUE":""
   },
   {
    "STRUCOBJN":"ZYCDS_DUE_MAT_LIST2",
    "NAME":"ENDUSERTEXT.LABEL",
    "POSITION":6,
    "VALUE":"'Material Due Date List'"
   },
   {
    "STRUCOBJN":"ZYCDS_DUE_MAT_LIST2",
    "NAME":"METADATA",
    "POSITION":7,
    "VALUE":""
   },
   {
    "STRUCOBJN":"ZYCDS_DUE_MAT_LIST2",
    "NAME":"METADATA",
    "POSITION":13,
    "VALUE":""
   },
   {
    "STRUCOBJN":"ZYCDS_DUE_MAT_LIST2",
    "NAME":"METADATA.ALLOWEXTENSIONS",
    "POSITION":14,
    "VALUE":"true"
   },
   {
    "STRUCOBJN":"ZYCDS_DUE_MAT_LIST2",
    "NAME":"METADATA.IGNOREPROPAGATEDANNOTATIONS",
    "POSITION":8,
    "VALUE":"true"
   },
   {
    "STRUCOBJN":"ZYCDS_DUE_MAT_LIST2",
    "NAME":"OBJECTMODEL.USAGETYPE",
    "POSITION":9,
    "VALUE":""
   },
   {
    "STRUCOBJN":"ZYCDS_DUE_MAT_LIST2",
    "NAME":"OBJECTMODEL.USAGETYPE.DATACLASS",
    "POSITION":12,
    "VALUE":"#MIXED"
   },
   {
    "STRUCOBJN":"ZYCDS_DUE_MAT_LIST2",
    "NAME":"OBJECTMODEL.USAGETYPE.SERVICEQUALITY",
    "POSITION":10,
    "VALUE":"#X"
   },
   {
    "STRUCOBJN":"ZYCDS_DUE_MAT_LIST2",
    "NAME":"OBJECTMODEL.USAGETYPE.SIZECATEGORY",
    "POSITION":11,
    "VALUE":"#S"
   }
  ]
 },
 {
  "table":"DDLDEPENDENCY",
  "data":
  [
   {
    "DDLNAME":"ZYCDS_DUE_MAT_LIST2",
    "OBJECTNAME":"ZYCDS_DUE_MAT_LIST2",
    "STATE":"N",
    "OBJECTTYPE":"STOB"
   }
  ]
 },
 {
  "table":"TADIR",
  "data":
  [
   {
    "PGMID":"R3TR",
    "OBJECT":"DDLS",
    "OBJ_NAME":"ZYCDS_DUE_MAT_LIST2",
    "KORRNUM":"",
    "SRCSYSTEM":"...",
    "AUTHOR":"SAP_CUSTOMER",
    "SRCDEP":"",
    "DEVCLASS":"Z_CPG",
    "GENFLAG":"",
    "EDTFLAG":"",
    "CPROJECT":" L",
    "MASTERLANG":"E",
    "VERSID":"",
    "PAKNOCHECK":"",
    "OBJSTABLTY":"",
    "COMPONENT":"",
    "CRELEASE":"",
    "DELFLAG":"",
    "TRANSLTTXT":"",
    "CREATED_ON":"2025-07-17",
    "CHECK_DATE":"2025-07-17",
    "CHECK_CFG":""
   }
  ]
 }
]